{
	"version": 1,
	"map_name": "Stroika",
	"map_path": "map_files/Stroika",
	"map_file": "Stroika.dmm",
	"space_ruin_levels": 0,
	"space_empty_levels": 0,
	"planetary": 1,
	"shuttles": {
		"cargo": "cargo_box",
		"ferry": "ferry_fancy",
		"whiteship": "whiteship_box"
		},
	"traits": [
		{
			"Mining": true,
			"Linkage": null,
			"Gravity": true,
			"Ice Ruins Underground": true,
			"Baseturf": "/turf/open/lava/plasma/ice_moon",
			"No Parallax": true
		},
		{
			"Mining": true,
			"Linkage": null,
			"Gravity": true,
			"Ice Ruins Underground": true,
			"Baseturf": "/turf/open/openspace/icemoon/keep_below",
			"No Parallax": true
		},
		{
			"Mining": true,
			"Linkage": null,
			"Gravity": true,
			"Ice Ruins Underground": true,
			"Baseturf": "/turf/open/openspace/icemoon/keep_below",
			"No Parallax": true
		},
		{
			"Mining": true,
			"Linkage": null,
			"Gravity": true,
			"Ice Ruins": true,
			"Baseturf": "/turf/open/openspace/icemoon/keep_below",
			"No Parallax": true
		},
		{
			"Mining": true,
			"Linkage": null,
			"Gravity": true,
			"Ice Ruins": true,
			"Weather_Snowstorm": true,
			"Baseturf": "/turf/open/openspace/icemoon/keep_below",
			"No Parallax": true
		}
	],
	"minetype": "none",
	"blacklist_file": "iceruinblacklist.txt",
	"job_changes": {
		"Prisoner": {
			"total_positions": 0,
			"spawn_positions": 0
		},
		"Captain": {
			"total_positions": 0,
			"spawn_positions": 0
		},
		"Head of Personnel": {
			"total_positions": 0,
			"spawn_positions": 0
		},
		"Head of Security": {
			"total_positions": 0,
			"spawn_positions": 0
		},
		"Research Director": {
			"total_positions": 0,
			"spawn_positions": 0
		},
		"Chief Engineer": {
			"total_positions": 0,
			"spawn_positions": 0
		},
		"Chief Medical Officer": {
			"total_positions": 0,
			"spawn_positions": 0
		},
		"Bridge Assistant": {
			"total_positions": 0,
			"spawn_positions": 0
		},
		"Veteran Security Advisor": {
			"total_positions": 0,
			"spawn_positions": 0
		},
		"Warden": {
			"total_positions": 0,
			"spawn_positions": 0
		},
		"Detective": {
			"total_positions": 0,
			"spawn_positions": 0
		},
		"Security Officer": {
			"total_positions": 0,
			"spawn_positions": 0
		},
		"Security Officer (Medical)": {
			"total_positions": 0,
			"spawn_positions": 0
		},
		"Security Officer (Engineering)": {
			"total_positions": 0,
			"spawn_positions": 0
		},
		"Security Officer (Science)": {
			"total_positions": 0,
			"spawn_positions": 0
		},
		"Security Officer (Cargo)": {
			"total_positions": 0,
			"spawn_positions": 0
		},
		"Station Engineer": {
			"total_positions": 0,
			"spawn_positions": 0
		},
		"Atmospheric Technician": {
			"total_positions": 0,
			"spawn_positions": 0
		},
		"Coroner": {
			"total_positions": 0,
			"spawn_positions": 0
		},
		"Medical Doctor": {
			"total_positions": 0,
			"spawn_positions": 0
		},
		"Paramedic": {
			"total_positions": 0,
			"spawn_positions": 0
		},
		"Chemist": {
			"total_positions": 0,
			"spawn_positions": 0
		},
		"Scientist": {
			"total_positions": 0,
			"spawn_positions": 0
		},
		"Roboticist": {
			"total_positions": 0,
			"spawn_positions": 0
		},
		"Geneticist": {
			"total_positions": 0,
			"spawn_positions": 0
		},
		"Quartermaster": {
			"total_positions": 0,
			"spawn_positions": 0
		},
		"Cargo Technician": {
			"total_positions": 0,
			"spawn_positions": 0
		},
		"Cargo Gorilla": {
			"total_positions": 0,
			"spawn_positions": 0
		},
		"Shaft Miner": {
			"total_positions": 0,
			"spawn_positions": 0
		},
		"Bitrunner": {
			"total_positions": 0,
			"spawn_positions": 0
		},
		"Bartender": {
			"total_positions": 0,
			"spawn_positions": 0
		},
		"Botanist": {
			"total_positions": 0,
			"spawn_positions": 0
		},
		"Cook": {
			"total_positions": 0,
			"spawn_positions": 0
		},
		"Chef": {
			"total_positions": 0,
			"spawn_positions": 0
		},
		"Janitor": {
			"total_positions": 0,
			"spawn_positions": 0
		},
		"Clown": {
			"total_positions": 0,
			"spawn_positions": 0
		},
		"Mime": {
			"total_positions": 0,
			"spawn_positions": 0
		},
		"Curator": {
			"total_positions": 0,
			"spawn_positions": 0
		},
		"Lawyer": {
			"total_positions": 0,
			"spawn_positions": 0
		},
		"Chaplain": {
			"total_positions": 0,
			"spawn_positions": 0
		},
		"Psychologist": {
			"total_positions": 0,
			"spawn_positions": 0
		},
		"Pun Pun": {
			"total_positions": 0,
			"spawn_positions": 0
		},
		"Assistant": {
			"suit": "/obj/item/clothing/suit/hooded/wintercoat/eva",
			"suit_stored": "/obj/item/tank/internals/emergency_oxygen/double",
			"box": "/obj/item/storage/box/survival/mining/bonus",
			"backpack_contents": [
				"/obj/item/construction/rcd/loaded/upgraded",
				"/obj/item/pipe_dispenser",
				"/obj/item/clothing/glasses/sunglasses",
				"/obj/item/storage/medkit/tactical_lite",
				"/obj/item/stack/sheet/mineral/wood/fifty",
				"/obj/item/electronics/apc",
				"/obj/item/wallframe/apc",
				"/obj/item/climbing_hook/infinite",
				"/obj/item/stack/sheet/glass/fifty",
				"/obj/item/stack/sheet/iron/fifty",
				"/obj/item/circuitboard/machine/ore_redemption",
				"/obj/item/storage/part_replacer/bluespace/tier2",
				"/obj/item/circuitboard/computer/rdconsole",
				"/obj/item/circuitboard/machine/circuit_imprinter",
				"/obj/item/circuitboard/machine/protolathe",
				"/obj/item/circuitboard/machine/autolathe"
			],
			"belt": "/obj/item/storage/belt/utility/chief/full",
			"glasses": "/obj/item/clothing/glasses/meson/engine",
			"gloves": "/obj/item/clothing/gloves/color/yellow",
			"head": "/obj/item/clothing/head/utility/hardhat/welding/white/up",
			"shoes": "/obj/item/clothing/shoes/winterboots/ice_boots/eva",
			"l_hand": "/obj/item/gun/energy/recharge/kinetic_accelerator",
			"r_hand": "/obj/item/pickaxe/silver",
			"implants": [
				"/obj/item/implant/spell"
			],
			"skillchips": [
				"/obj/item/skillchip/job/engineer"
			]
		}
	}
}
